hidrowebsdk/__init__.py
hidrowebsdk/client.py
hidrowebsdk-0.2.0.dist-info/licenses/LICENSE
hidrowebsdk-0.2.0.dist-info/METADATA
hidrowebsdk-0.2.0.dist-info/WHEEL
hidrowebsdk-0.2.0.dist-info/top_level.txt
hidrowebsdk-0.2.0.dist-info/RECORD
