Metadata-Version: 2.4
Name: hidrowebsdk
Version: 0.2.0
Summary: Python SDK to communicate with ANA's HidroWeb API for hydrological and pluviometric data
Author-email: Julio Werner <julio.werner@nvxtech.com.br>
License: MIT
Project-URL: Homepage, https://nvxtech.github.io/hidrowebsdk/
Project-URL: Repository, https://github.com/NVXtech/hidrowebsdk
Project-URL: Issues, https://github.com/NVXtech/hidrowebsdk/issues
Project-URL: Documentation, https://nvxtech.github.io/hidrowebsdk/
Keywords: hydrology,water,api,brazil,ana,hidroweb
Classifier: Development Status :: 3 - Alpha
Classifier: Intended Audience :: Developers
Classifier: License :: OSI Approved :: MIT License
Classifier: Operating System :: OS Independent
Classifier: Programming Language :: Python :: 3
Classifier: Programming Language :: Python :: 3.11
Classifier: Programming Language :: Python :: 3.12
Classifier: Topic :: Scientific/Engineering :: Hydrology
Requires-Python: >=3.11
License-File: LICENSE
Requires-Dist: httpx
Requires-Dist: pandas
Provides-Extra: dev
Requires-Dist: pytest; extra == "dev"
Requires-Dist: pytest-asyncio; extra == "dev"
Requires-Dist: sphinx; extra == "dev"
Requires-Dist: sphinx-rtd-theme; extra == "dev"
Dynamic: license-file
